aiocsv_utils/__init__.py
aiocsv_utils/convert.py
aiocsv_utils/read.py
aiocsv_utils/write.py
aiocsv_utils-0.0.1.dist-info/LICENSE
aiocsv_utils-0.0.1.dist-info/METADATA
aiocsv_utils-0.0.1.dist-info/WHEEL
aiocsv_utils-0.0.1.dist-info/top_level.txt
aiocsv_utils-0.0.1.dist-info/RECORD
